<?xml version="1.0" encoding="utf-8"?>
<Users>
  <User ID="0">
    <FirstName>Jason</FirstName>
    <LastName>Merrill</LastName>
    <BirthDate>16/08/1983</BirthDate>
    <Username>jasonlmerrill</Username>
    <StartDate>16/08/1983</StartDate>
    <Gender>Male</Gender>
    <CurrentWeight>155</CurrentWeight>
    <CurrentHeight>5'8"</CurrentHeight>
    <Password>password</Password>
    <Workout>Cardio</Workout>
  </User>
  <User ID="1">
    <FirstName>Jason</FirstName>
    <LastName>Merrill</LastName>
    <BirthDate>07/04/2017</BirthDate>
    <Username>jasonlmerrill</Username>
    <StartDate>07/04/2017</StartDate>
    <Gender>Male</Gender>
    <CurrentWeight>155</CurrentWeight>
    <CurrentHeight>5'8"</CurrentHeight>
    <Password>asdf</Password>
    <Workout>Gain Muscle</Workout>
  </User>
</Users>